CHANGES.rst
README.rst
setup.py
bobtemplates/__init__.py
bobtemplates.fanstatic.egg-info/PKG-INFO
bobtemplates.fanstatic.egg-info/SOURCES.txt
bobtemplates.fanstatic.egg-info/dependency_links.txt
bobtemplates.fanstatic.egg-info/namespace_packages.txt
bobtemplates.fanstatic.egg-info/not-zip-safe
bobtemplates.fanstatic.egg-info/requires.txt
bobtemplates.fanstatic.egg-info/top_level.txt
bobtemplates/fanstatic/__init__.py
bobtemplates/fanstatic/package/.mrbob.ini
bobtemplates/fanstatic/package/CHANGES.txt.bob
bobtemplates/fanstatic/package/LICENSE.txt
bobtemplates/fanstatic/package/MANIFEST.in.bob
bobtemplates/fanstatic/package/README.txt.bob
bobtemplates/fanstatic/package/bootstrap.py
bobtemplates/fanstatic/package/buildout.cfg.bob
bobtemplates/fanstatic/package/setup.py.bob
bobtemplates/fanstatic/package/js/__init__.py
bobtemplates/fanstatic/package/js/+library.name+/__init__.py.bob
bobtemplates/fanstatic/package/js/+library.name+/test_+library.name+.txt.bob
bobtemplates/fanstatic/package/js/+library.name+/resources/README.txt