Metadata-Version: 1.1
Name: bobtemplates.fanstatic
Version: 0.1-1
Summary: mr.bob template for Fanstatic packages
Home-page: https://github.com/teixas/bobtemplates.fanstatic
Author: Nuno Teixeira
Author-email: teixas@gmail.com
License: BSD
Platform: UNKNOWN
Classifier: Development Status :: 3 - Alpha
Classifier: Environment :: Console
Classifier: Intended Audience :: Developers
Classifier: License :: OSI Approved :: BSD License
Classifier: Natural Language :: English
Classifier: Operating System :: OS Independent
Classifier: Programming Language :: Python
Classifier: Topic :: Software Development :: Code Generators
Classifier: Topic :: Utilities
